parsek.py
parsek-2.2.1.dist-info/LICENSE
parsek-2.2.1.dist-info/WHEEL
parsek-2.2.1.dist-info/METADATA
parsek-2.2.1.dist-info/RECORD
