Metadata-Version: 2.1
Name: parsek
Version: 2.2.1
Summary: Pure Python, no-dependency, single source file parser combinator library
Author-email: Anton Petersen <quarkatron@gmail.com>
Requires-Python: >=3.10
Classifier: License :: OSI Approved :: MIT License
Classifier: Programming Language :: Python :: 3
Classifier: Programming Language :: Python :: 3 :: Only
Classifier: Programming Language :: Python :: 3.10
Classifier: Programming Language :: Python :: 3.11
Classifier: Programming Language :: Python :: 3.12
Classifier: Programming Language :: Python :: 3.13
Project-URL: Home, https://github.com/anptrs/parsek
